netfleece/__init__.py
netfleece/b64stream.py
netfleece/netfleece.py
netfleece-0.1.3.1.dist-info/LICENSE
netfleece-0.1.3.1.dist-info/METADATA
netfleece-0.1.3.1.dist-info/WHEEL
netfleece-0.1.3.1.dist-info/entry_points.txt
netfleece-0.1.3.1.dist-info/top_level.txt
netfleece-0.1.3.1.dist-info/RECORD
