Metadata-Version: 2.1
Name: netfleece
Version: 0.1.3.1
Summary: Microsoft .NET Remoting Binary Format (MS-NRBF) to JSON parser
Home-page: https://gitlab.com/malie-library/netfleece
Author: nago
Author-email: nago@malie.io
License: MIT License
Platform: UNKNOWN
Classifier: Development Status :: 2 - Pre-Alpha
Classifier: License :: OSI Approved :: MIT License
Classifier: Natural Language :: English
Classifier: Operating System :: OS Independent
Classifier: Programming Language :: Python :: 3
Classifier: Topic :: Software Development :: Disassemblers
License-File: LICENSE
